[
    {
        "rep": "Zac Messinger",
        "repType": "Customer Success Engineer",
        "activityDate": "2020-09-28",
        "recordType": "Internal",
        "hours": 0.5,
        "description": "***Team QM - Weekly Huddle***",
        "account": "CS Internal Activities",
        "type": "Group/Company Meeting"
    },
    {
        "rep": "Zac Messinger",
        "repType": "Customer Success Engineer",
        "activityDate": "2020-09-28",
        "hours": 1,
        "description": "Dashboard Updates",
        "type": "Production Support",
        "account": "Norton Software",
        "recordType": "External"
    },
    {
        "rep": "Zac Messinger",
        "repType": "Customer Success Engineer",
        "activityDate": "2020-09-28",
        "hours": 1,
        "description": "Event Document for Ben",
        "type": "Production Support",
        "account": "Norton Software",
        "recordType": "External"
    },
    {
        "rep": "Zac Messinger",
        "repType": "Customer Success Engineer",
        "activityDate": "2020-09-28",
        "recordType": "Internal",
        "hours": 0.5,
        "description": "Email Batching",
        "account": "CS Internal Activities",
        "type": "Internal Meetings"
    },
    {
        "rep": "Zac Messinger",
        "repType": "Customer Success Engineer",
        "activityDate": "2020-09-28",
        "hours": 1.5,
        "description": "Training Prep",
        "type": "Production Support",
        "account": "Norton Software",
        "recordType": "External"
    },
    {
        "rep": "Zac Messinger",
        "repType": "Customer Success Engineer",
        "activityDate": "2020-09-28",
        "hours": 0.5,
        "description": "Dasboard YSOD",
        "type": "Production Support",
        "account": "ClaroPay",
        "recordType": "External"
    },
    {
        "rep": "Zac Messinger",
        "repType": "Customer Success Engineer",
        "activityDate": "2020-09-28",
        "hours": 1,
        "description": "API Training",
        "type": "Value-Based Training",
        "account": "Norton Software",
        "recordType": "External"
    },
    {
        "rep": "Zac Messinger",
        "repType": "Customer Success Engineer",
        "activityDate": "2020-09-28",
        "recordType": "Internal",
        "hours": 0.5,
        "description": "Zac<>Dishon<>Megi  Weekly Account Alignment Meeting",
        "account": "CS Internal Activities",
        "type": "Internal Meetings"
    },
    {
        "rep": "Zac Messinger",
        "repType": "Customer Success Engineer",
        "activityDate": "2020-09-28",
        "hours": 0.5,
        "description": "Renewal discussion w/ Brynn",
        "type": "Business Review Call",
        "account": "Taco Bell",
        "recordType": "External"
    },
    {
        "rep": "Zac Messinger",
        "repType": "Customer Success Engineer",
        "activityDate": "2020-09-28",
        "hours": 0.75,
        "description": "NCX ops funnel review w/ Kai",
        "type": "Business Review Call",
        "account": "Herbalife",
        "recordType": "External"
    },
    {
        "rep": "Zac Messinger",
        "repType": "Customer Success Engineer",
        "activityDate": "2020-09-28",
        "hours": 0.5,
        "description": "Android API support config review",
        "type": "Production Support",
        "account": "ClaroPay",
        "recordType": "External"
    },
    {
        "rep": "Zac Messinger",
        "repType": "Customer Success Engineer",
        "activityDate": "2020-09-29",
        "recordType": "Internal",
        "hours": 0.5,
        "description": "Email Batching",
        "account": "CS Internal Activities",
        "type": "Internal Meetings"
    },
    {
        "rep": "Zac Messinger",
        "repType": "Customer Success Engineer",
        "activityDate": "2020-09-29",
        "hours": 0.5,
        "description": "CSE Montly Chat",
        "type": "Internal Meetings",
        "account": "CS Internal Activities",
        "recordType": "Internal"
    },
    {
        "rep": "Zac Messinger",
        "repType": "Customer Success Engineer",
        "activityDate": "2020-09-29",
        "hours": 0.5,
        "description": "Norton config walk through w/ Thomas",
        "type": "Internal Meetings",
        "account": "CS Internal Activities",
        "recordType": "Internal"
    },
    {
        "rep": "Zac Messinger",
        "repType": "Customer Success Engineer",
        "activityDate": "2020-09-29",
        "hours": 2,
        "description": "CH1 Config Review",
        "type": "Production Support",
        "account": "Norton Software",
        "recordType": "External"
    },
    {
        "rep": "Zac Messinger",
        "repType": "Customer Success Engineer",
        "activityDate": "2020-09-29",
        "hours": 0.4166666666666667,
        "description": "CST Chat w/ Mark",
        "type": "Internal Meetings",
        "account": "CS Internal Activities",
        "recordType": "Internal"
    }
]